[
  {
    "title": "lord of the rings",
    "color": "blue"
  },
  {
    "title": "bugs life",
    "color": "red"
  },
  {
    "title": "bugs",
    "color": "gold"
  },
  {
    "title": "tyf",
    "color": "blue"
  },
  {
    "title": "Chois",
    "color": "green"
  },
  {
    "title": "Loofer",
    "color": "Black"
  },
  {
    "title": "iiii",
    "color": "brown"
  },
  {
    "title": "quora",
    "color": "silver"
  },
  {
    "title": "gift",
    "color": "red"
  },
  {
    "title": "shuhad",
    "color": "white"
  },
  {
    "title": "red",
    "color": "pink"
  },
  {
    "title": "lop",
    "color": "red"
  },
  {
    "title": "this is a test",
    "color": "super brown cow"
  },
  {
    "title": "gift",
    "color": "red"
  },
  {
    "title": "hoep it works",
    "color": "black magic"
  },
  {
    "title": "rer",
    "color": "reewq"
  },
  {
    "title": "gdgf",
    "color": "dfgdf"
  },
  {
    "title": "new",
    "color": "gold"
  },
  {
    "title": "harry potter",
    "color": "red"
  },
  {
    "title": "tyrt",
    "color": "gfh"
  },
  {
    "title": "f",
    "color": "gfnh"
  },
  {
    "title": "as",
    "color": "sdfg"
  }
]